cc_sessions_drupal/__init__.py
cc_sessions_drupal/install.py
cc_sessions_drupal/python/drupal_state.py
cc_sessions_drupal/python/task_detector.py
cc_sessions_drupal-0.1.1.dist-info/licenses/LICENSE
cc_sessions_drupal-0.1.1.dist-info/METADATA
cc_sessions_drupal-0.1.1.dist-info/WHEEL
cc_sessions_drupal-0.1.1.dist-info/entry_points.txt
cc_sessions_drupal-0.1.1.dist-info/top_level.txt
cc_sessions_drupal-0.1.1.dist-info/RECORD
