Metadata-Version: 2.4
Name: cc-sessions-drupal
Version: 0.1.1
Summary: Drupal-optimized extension for cc-sessions with quality gates, task templates, and specialized agents
Author-email: zorz <zorz@example.com>
License: MIT
Project-URL: Homepage, https://github.com/gkastanis/cc-sessions-drupal
Project-URL: Documentation, https://github.com/gkastanis/cc-sessions-drupal#readme
Project-URL: Repository, https://github.com/gkastanis/cc-sessions-drupal.git
Project-URL: Issues, https://github.com/gkastanis/cc-sessions-drupal/issues
Keywords: drupal,drupal-10,drupal-11,cc-sessions,claude-code,phpcs,behat,quality-gates,workflow,development
Classifier: Development Status :: 4 - Beta
Classifier: Intended Audience :: Developers
Classifier: License :: OSI Approved :: MIT License
Classifier: Programming Language :: Python :: 3
Classifier: Programming Language :: Python :: 3.8
Classifier: Programming Language :: Python :: 3.9
Classifier: Programming Language :: Python :: 3.10
Classifier: Programming Language :: Python :: 3.11
Classifier: Programming Language :: Python :: 3.12
Classifier: Operating System :: MacOS
Classifier: Operating System :: POSIX :: Linux
Classifier: Operating System :: Microsoft :: Windows
Classifier: Topic :: Software Development
Classifier: Topic :: Software Development :: Quality Assurance
Requires-Python: >=3.8
License-File: LICENSE
Requires-Dist: cc-sessions>=0.3.0
Provides-Extra: dev
Requires-Dist: pytest>=7.0.0; extra == "dev"
Requires-Dist: black>=23.0.0; extra == "dev"
Requires-Dist: flake8>=6.0.0; extra == "dev"
Dynamic: license-file
